{"schema_version":"r1.2","updated_at":"2025-09-12T21:01:06+00:00","ts":"2025-09-12T21:01:06+00:00","version":"1.2-hourly","pipeline":"intraday","gauges":{"rpm":{"pct":59.288256227758005,"label":"Breadth"},"speed":{"pct":29.192982456140353,"label":"Momentum"},"fuel":{"pct":45.0,"state":"idle","label":"Squeeze"},"water":{"pct":8.0,"label":"Volatility"},"oil":{"psi":104.0,"label":"Liquidity"},"squeezeDaily":{"pct":45.09}},"odometers":{"squeezeCompressionPct":45.0},"summary":{"breadthIdx":59.288256227758005,"momentumIdx":29.192982456140353},"sectorCards":[{"sector":"Information Technology","outlook":"Bullish","spark":[]},{"sector":"Materials","outlook":"Bullish","spark":[]},{"sector":"Healthcare","outlook":"Bullish","spark":[]},{"sector":"Communication Services","outlook":"Bullish","spark":[]},{"sector":"Real Estate","outlook":"Bullish","spark":[]},{"sector":"Energy","outlook":"Bullish","spark":[]},{"sector":"Consumer Staples","outlook":"Bullish","spark":[]},{"sector":"Consumer Discretionary","outlook":"Bearish","spark":[]},{"sector":"Financials","outlook":"Bearish","spark":[]},{"sector":"Utilities","outlook":"Bullish","spark":[]},{"sector":"Industrials","outlook":"Bullish","spark":[]}],"outlook":{"sectors":{"financials":{"nh":101,"nl":139,"up":206,"down":540,"netNH":-38,"netUD":-334,"spark":[]},"consumer staples":{"nh":39,"nl":30,"up":63,"down":134,"netNH":9,"netUD":-71,"spark":[]},"real estate":{"nh":54,"nl":14,"up":69,"down":163,"netNH":40,"netUD":-94,"spark":[]},"communication services":{"nh":48,"nl":20,"up":87,"down":120,"netNH":28,"netUD":-33,"spark":[]},"utilities":{"nh":21,"nl":3,"up":46,"down":47,"netNH":18,"netUD":-1,"spark":[]},"information technology":{"nh":120,"nl":64,"up":158,"down":414,"netNH":56,"netUD":-256,"spark":[]},"industrials":{"nh":119,"nl":47,"up":155,"down":413,"netNH":72,"netUD":-258,"spark":[]},"energy":{"nh":44,"nl":18,"up":62,"down":133,"netNH":26,"netUD":-71,"spark":[]},"healthcare":{"nh":159,"nl":148,"up":225,"down":589,"netNH":11,"netUD":-364,"spark":[]},"materials":{"nh":72,"nl":14,"up":73,"down":139,"netNH":58,"netUD":-66,"spark":[]},"consumer discretionary":{"nh":56,"nl":75,"up":104,"down":335,"netNH":-19,"netUD":-231,"spark":[]}},"sectorCards":[{"sector":"Information Technology","outlook":"Bullish","spark":[]},{"sector":"Materials","outlook":"Bullish","spark":[]},{"sector":"Healthcare","outlook":"Bullish","spark":[]},{"sector":"Communication Services","outlook":"Bullish","spark":[]},{"sector":"Real Estate","outlook":"Bullish","spark":[]},{"sector":"Energy","outlook":"Bullish","spark":[]},{"sector":"Consumer Staples","outlook":"Bullish","spark":[]},{"sector":"Consumer Discretionary","outlook":"Bearish","spark":[]},{"sector":"Financials","outlook":"Bearish","spark":[]},{"sector":"Utilities","outlook":"Bullish","spark":[]},{"sector":"Industrials","outlook":"Bullish","spark":[]}]},"signals":{}}
