{"version":"r-intraday-v1","updated_at":"2026-02-18 06:55:56","updated_at_utc":"2026-02-18T13:55:56Z","mode":"intraday","metrics":{"breadth_10m_pct":52.73,"momentum_10m_pct":46.3,"squeeze_psi_10m_pct":100.0,"squeeze_expansion_pct":0.0,"squeeze_pct":100.0,"liquidity_psi":143.0,"volatility_pct":0.128,"ema_sign":-1,"ema_gap_pct":-0.033,"breadth_align_fast_pct":81.82,"momentum_combo_10m_pct":46.3,"riskOn_10m_pct":37.5},"intraday":{"sectorDirection10m":{"risingPct":7.69},"riskOn10m":{"riskOnPct":37.5},"overall10m":{"state":"bear","score":46,"components":{"ema10":-2,"momentum":-2,"breadth":1,"squeeze":-10,"liquidity":10,"riskOn":-1},"lastChanged":"2026-02-18T13:55:58Z"}},"engineLights":{"10m":{"state":"bear","score":46,"components":{"ema10":-2,"momentum":-2,"breadth":1,"squeeze":-10,"liquidity":10,"riskOn":-1},"lastChanged":"2026-02-18T13:55:58Z"},"signals":{"sigOverall10m":{"state":"neutral","recentCross":false,"lastChanged":"2026-02-17T18:05:09Z","reason":"overall(10m)=neutral"},"sigEMA10m":{"state":"neutral","recentCross":false,"lastChanged":"2026-02-17T18:05:09Z","reason":"EMA10 vs 20 (10m) posture"},"sigAccel10m":{"state":"neutral","recentCross":false,"lastChanged":"2026-02-17T18:05:09Z","reason":"Δ(breadth+momentum)=n/a"},"sigCandle10m":{"state":"neutral","recentCross":false,"lastChanged":"2026-02-17T18:05:09Z","reason":"close>open → bull; close<open → bear"}}},"sectorCards":[{"sector":"Information Technology","breadth_pct":0.0,"momentum_pct":0.0,"nh":0,"nl":0,"up":0,"down":0,"outlook":"Bearish"},{"sector":"Materials","breadth_pct":55.56,"momentum_pct":63.64,"nh":35,"nl":28,"up":35,"down":20,"outlook":"Bullish"},{"sector":"Health Care","breadth_pct":0.0,"momentum_pct":0.0,"nh":0,"nl":0,"up":0,"down":0,"outlook":"Bearish"},{"sector":"Communication Services","breadth_pct":35.0,"momentum_pct":26.67,"nh":14,"nl":26,"up":8,"down":22,"outlook":"Bearish"},{"sector":"Real Estate","breadth_pct":50.0,"momentum_pct":57.14,"nh":7,"nl":7,"up":4,"down":3,"outlook":"Neutral"},{"sector":"Energy","breadth_pct":55.1,"momentum_pct":50.0,"nh":27,"nl":22,"up":14,"down":14,"outlook":"Neutral"},{"sector":"Consumer Staples","breadth_pct":25.81,"momentum_pct":15.0,"nh":8,"nl":23,"up":3,"down":17,"outlook":"Bearish"},{"sector":"Consumer Discretionary","breadth_pct":37.1,"momentum_pct":33.33,"nh":23,"nl":39,"up":12,"down":24,"outlook":"Bearish"},{"sector":"Financials","breadth_pct":33.85,"momentum_pct":36.59,"nh":22,"nl":43,"up":15,"down":26,"outlook":"Bearish"},{"sector":"Utilities","breadth_pct":35.71,"momentum_pct":36.36,"nh":5,"nl":9,"up":4,"down":7,"outlook":"Bearish"},{"sector":"Industrials","breadth_pct":43.18,"momentum_pct":38.98,"nh":38,"nl":50,"up":23,"down":36,"outlook":"Bearish"},{"sector":"Healthcare","breadth_pct":47.85,"momentum_pct":47.25,"nh":78,"nl":85,"up":43,"down":48,"outlook":"Neutral"},{"sector":"tech","breadth_pct":30.28,"momentum_pct":34.58,"nh":43,"nl":99,"up":37,"down":70,"outlook":"Bearish"}],"meta":{"last_full_run_utc":"2026-02-18T13:55:56Z"}}