{"sectorCards": [{"sector": "Communication Services", "breadth_pct": 80.83, "momentum_pct": 78.0, "nh": 97, "nl": 23, "up": 78, "down": 22}, {"sector": "Consumer Discretionary", "breadth_pct": 87.23, "momentum_pct": 85.78, "nh": 246, "nl": 36, "up": 187, "down": 31}, {"sector": "Consumer Staples", "breadth_pct": 76.03, "momentum_pct": 65.22, "nh": 92, "nl": 29, "up": 60, "down": 32}, {"sector": "Energy", "breadth_pct": 49.57, "momentum_pct": 75.24, "nh": 58, "nl": 59, "up": 79, "down": 26}, {"sector": "Financials", "breadth_pct": 91.67, "momentum_pct": 88.24, "nh": 517, "nl": 47, "up": 300, "down": 40}, {"sector": "Healthcare", "breadth_pct": 84.08, "momentum_pct": 86.43, "nh": 544, "nl": 103, "up": 414, "down": 65}, {"sector": "Industrials", "breadth_pct": 81.19, "momentum_pct": 83.45, "nh": 246, "nl": 57, "up": 232, "down": 46}, {"sector": "Materials", "breadth_pct": 87.78, "momentum_pct": 86.78, "nh": 158, "nl": 22, "up": 105, "down": 16}, {"sector": "Real Estate", "breadth_pct": 68.5, "momentum_pct": 56.99, "nh": 87, "nl": 40, "up": 53, "down": 40}, {"sector": "Utilities", "breadth_pct": 61.82, "momentum_pct": 22.5, "nh": 34, "nl": 21, "up": 9, "down": 31}, {"sector": "tech", "breadth_pct": 81.04, "momentum_pct": 83.53, "nh": 312, "nl": 73, "up": 279, "down": 55}]}