{"sectorCards": [{"sector": "Communication Services", "breadth_pct": 21.24, "momentum_pct": 35.29, "nh": 24, "nl": 89, "up": 42, "down": 77}, {"sector": "Consumer Discretionary", "breadth_pct": 28.93, "momentum_pct": 37.63, "nh": 57, "nl": 140, "up": 73, "down": 121}, {"sector": "Consumer Staples", "breadth_pct": 42.5, "momentum_pct": 44.34, "nh": 34, "nl": 46, "up": 47, "down": 59}, {"sector": "Energy", "breadth_pct": 54.29, "momentum_pct": 60.61, "nh": 38, "nl": 32, "up": 60, "down": 39}, {"sector": "Financials", "breadth_pct": 37.39, "momentum_pct": 38.97, "nh": 89, "nl": 149, "up": 129, "down": 202}, {"sector": "Healthcare", "breadth_pct": 40.34, "momentum_pct": 52.44, "nh": 167, "nl": 247, "up": 236, "down": 214}, {"sector": "Industrials", "breadth_pct": 51.02, "momentum_pct": 45.68, "nh": 125, "nl": 120, "up": 127, "down": 151}, {"sector": "Materials", "breadth_pct": 19.33, "momentum_pct": 43.93, "nh": 23, "nl": 96, "up": 47, "down": 60}, {"sector": "Real Estate", "breadth_pct": 36.17, "momentum_pct": 35.64, "nh": 34, "nl": 60, "up": 36, "down": 65}, {"sector": "Utilities", "breadth_pct": 84.09, "momentum_pct": 91.67, "nh": 37, "nl": 7, "up": 44, "down": 4}, {"sector": "tech", "breadth_pct": 40.96, "momentum_pct": 39.77, "nh": 145, "nl": 209, "up": 136, "down": 206}]}