{"version":"r1h-v1-fast","updated_at":"2025-11-28 11:21:32","updated_at_utc":"2025-11-28T18:21:32Z","metrics":{"breadth_1h_pct":55.96,"breadth_align_1h_pct":null,"breadth_align_1h_pct_fast":null,"breadth_bar_1h_pct":null,"breadth_bar_1h_pct_fast":null,"momentum_1h_pct":44.26,"momentum_combo_1h_pct":63.25,"squeeze_1h_pct":11.770475555440939,"squeeze_psi_1h_pct":88.22952444455906,"liquidity_1h":186.63755834003376,"volatility_1h_pct":0.232,"volatility_1h_scaled":1.45,"breadth_slow_pct":55.96,"momentum_slow_pct":44.26},"hourly":{"sectorDirection1h":{"risingPct":27.27},"riskOn1h":{"riskOnPct":50.0},"overall1h":{"state":"bull","score":74,"components":{"ema10":13,"momentum":7,"breadth":2,"squeeze":-8,"liquidity":10,"riskOn":0}},"signals":{"sigEMA1hBullCross":{"active":false,"severity":"info","reason":"","lastChanged":"2025-11-21T20:20:37Z"},"sigEMA1hBearCross":{"active":false,"severity":"warn","reason":"","lastChanged":"2025-11-20T19:00:50Z"},"sigSMI1hBullCross":{"active":true,"severity":"info","reason":"SMI %K crossed above %D (1h)","lastChanged":"2025-11-28T18:21:32Z"},"sigSMI1hBearCross":{"active":false,"severity":"warn","reason":"","lastChanged":"2025-11-26T20:19:58Z"},"sigOverall1h":{"state":"bull","lastChanged":"2025-11-28T18:21:32Z"}}},"sectorCards":[{"sector":"Communication Services","breadth_pct":67.69,"momentum_pct":48.65,"nh":44,"nl":21,"up":54,"down":57},{"sector":"Consumer Discretionary","breadth_pct":44.9,"momentum_pct":33.02,"nh":66,"nl":81,"up":70,"down":142},{"sector":"Consumer Staples","breadth_pct":70.49,"momentum_pct":56.0,"nh":43,"nl":18,"up":56,"down":44},{"sector":"Energy","breadth_pct":77.14,"momentum_pct":43.14,"nh":54,"nl":16,"up":44,"down":58},{"sector":"Financials","breadth_pct":32.43,"momentum_pct":22.6,"nh":84,"nl":175,"up":80,"down":274},{"sector":"Healthcare","breadth_pct":54.58,"momentum_pct":47.67,"nh":143,"nl":119,"up":205,"down":225},{"sector":"Industrials","breadth_pct":60.25,"momentum_pct":47.41,"nh":97,"nl":64,"up":119,"down":132},{"sector":"Materials","breadth_pct":83.16,"momentum_pct":58.12,"nh":79,"nl":16,"up":68,"down":49},{"sector":"Real Estate","breadth_pct":41.94,"momentum_pct":63.37,"nh":26,"nl":36,"up":64,"down":37},{"sector":"Utilities","breadth_pct":87.5,"momentum_pct":75.68,"nh":28,"nl":4,"up":28,"down":9},{"sector":"tech","breadth_pct":64.61,"momentum_pct":49.65,"nh":115,"nl":63,"up":142,"down":144}],"meta":{"cards_fresh":true,"after_hours":false}}