{"version":"r30m-v6-truebridge-simplified-fixed","updated_at":"2026-06-04 12:30:51","updated_at_utc":"2026-06-04T19:30:51Z","metrics":{"overall_30m_score":55.0,"overall_30m_state":"neutral","ema_sign_30m":1,"ema10_dist_30m_pct":0.2183,"ema10_posture_30m_pct":68.19,"ema10_gt_ema20":true,"ema_gap_10_20_pct":0.1699,"structure_tier":"above50_reclaim","structure_score_30m":56.0,"ema_reclaim_tol_pct":0.1,"ema50_reclaim_tol_pct":0.15,"price_above_ema50_30m":true,"ema818_gap_pct":0.1976,"ema8_ema18_posture_30m_pct":66.47,"smi_30m":93.3674,"smi_signal_30m":88.3499,"smi_30m_pct":96.68,"momentum_combo_30m_pct":74.89,"squeeze_psi_30m_pct":2.52,"squeeze_expansion_30m_pct":97.48,"breadth_align_pct":72.73,"breadth_barup_pct":72.73,"breadth_30m_pct":72.73,"riskOn_30m_pct":75.0,"psi_window_30m_bars":26,"fetch_days_30M":30},"thirtyMin":{"overall30m":{"state":"neutral","score":55.0,"components":{"structure":26.88,"momentum":20.22,"breadth":10.91,"squeeze":9.75,"smiBonus":3.0},"lastChanged":"2026-06-04T19:30:51Z"}},"sectorEtfCards":[{"sector":"information technology","symbol":"XLK","aligned":true,"barup":true},{"sector":"materials","symbol":"XLB","aligned":false,"barup":true},{"sector":"health care","symbol":"XLV","aligned":true,"barup":true},{"sector":"communication services","symbol":"XLC","aligned":true,"barup":false},{"sector":"real estate","symbol":"XLRE","aligned":true,"barup":true},{"sector":"energy","symbol":"XLE","aligned":true,"barup":false},{"sector":"consumer staples","symbol":"XLP","aligned":false,"barup":false},{"sector":"consumer discretionary","symbol":"XLY","aligned":true,"barup":true},{"sector":"financials","symbol":"XLF","aligned":true,"barup":true},{"sector":"utilities","symbol":"XLU","aligned":false,"barup":true},{"sector":"industrials","symbol":"XLI","aligned":true,"barup":true}],"meta":{"after_hours":false},"engine21Alignment":{"ok":true,"tf":"30m","symbols":["SPY","QQQ","DIA","UVXY"],"alignmentState":"FULL_BULL_ALIGNMENT","alignmentScore":100,"bullishAligned":true,"bearishAligned":false,"bullishScore":100,"bearishScore":0,"components":{"SPY":{"symbol":"SPY","price":758.29,"ema10":756.8876757582658,"ema20":755.2339524650573,"direction":"BULL","barCount":200},"QQQ":{"symbol":"QQQ","price":743.2815,"ema10":741.2997489265963,"ema20":739.5533375561553,"direction":"BULL","barCount":200},"DIA":{"symbol":"DIA","price":517.47,"ema10":516.5174332783647,"ema20":514.9532286169266,"direction":"BULL","barCount":200},"UVXY":{"symbol":"UVXY","price":28.0888,"ema10":28.254160827319463,"ema20":28.650779415068435,"direction":"BULL_CONFIRM","barCount":200}},"updatedAt":"2026-06-04T19:31:00.941Z"}}