{"version":"r1h-v3-ema10dist-tvSMI-legacy","updated_at":"2026-01-02 11:26:49","updated_at_utc":"2026-01-02T18:26:49Z","metrics":{"trend_strength_1h_pct":32.0,"breadth_1h_pct":66.35,"momentum_1h_pct":58.83,"momentum_combo_1h_pct":26.16,"squeeze_1h_pct":84.51,"squeeze_psi_1h_pct":15.49,"ema_sign":-1,"ema10_dist_pct":-0.3396,"ema10_posture_1h_pct":21.7,"smi_1h":-10.605051438730957,"smi_signal_1h":2.918206756738157,"smi_1h_pct":44.7,"smi_bonus_pts":-5,"liquidity_1h":142.01,"volatility_1h_pct":0.383,"volatility_1h_scaled":2.39,"breadth_slow_pct":66.35,"momentum_slow_pct":58.83},"hourly":{"sectorDirection1h":{"risingPct":81.82},"riskOn1h":{"riskOnPct":50.0},"overall1h":{"state":"bear","score":32,"components":{"ema10":-23,"momentum":-12,"breadth":5,"squeeze":7,"liquidity":10,"riskOn":0,"smiBonus":-5}},"signals":{"sigSMI1hBullCross":{"active":false,"severity":"info","reason":"","lastChanged":"2026-01-02T11:15:35Z"},"sigSMI1hBearCross":{"active":false,"severity":"info","reason":"","lastChanged":"2026-01-02T18:26:49Z"},"sigOverall1h":{"state":"bear","lastChanged":"2026-01-02T18:26:49Z"}}},"sectorCards":[{"sector":"Communication Services","breadth_pct":67.8,"momentum_pct":57.66,"nh":40,"nl":19,"up":64,"down":47},{"sector":"Consumer Discretionary","breadth_pct":81.46,"momentum_pct":76.57,"nh":123,"nl":28,"up":183,"down":56},{"sector":"Consumer Staples","breadth_pct":76.47,"momentum_pct":69.79,"nh":39,"nl":12,"up":67,"down":29},{"sector":"Energy","breadth_pct":88.89,"momentum_pct":86.62,"nh":120,"nl":15,"up":123,"down":19},{"sector":"Financials","breadth_pct":58.22,"momentum_pct":46.12,"nh":124,"nl":89,"up":184,"down":215},{"sector":"Healthcare","breadth_pct":36.12,"momentum_pct":40.08,"nh":108,"nl":191,"up":196,"down":293},{"sector":"Industrials","breadth_pct":82.76,"momentum_pct":63.6,"nh":168,"nl":35,"up":173,"down":99},{"sector":"Materials","breadth_pct":86.75,"momentum_pct":57.28,"nh":72,"nl":11,"up":59,"down":44},{"sector":"Real Estate","breadth_pct":68.66,"momentum_pct":75.89,"nh":46,"nl":21,"up":85,"down":27},{"sector":"Utilities","breadth_pct":89.47,"momentum_pct":76.79,"nh":34,"nl":4,"up":43,"down":13},{"sector":"tech","breadth_pct":58.44,"momentum_pct":62.72,"nh":90,"nl":64,"up":175,"down":104}],"meta":{"cards_fresh":true,"after_hours":false}}