{"version":"r1h-v14-stateful-lux-psi","updated_at":"2026-05-21 02:02:52","updated_at_utc":"2026-05-21T09:02:52Z","metrics":{"trend_strength_1h_pct":59.85,"breadth_1h_pct":72.11,"momentum_1h_pct":61.81,"momentum_combo_1h_pct":71.62,"squeeze_psi_1h_pct":97.89,"squeeze_expansion_pct":2.11,"squeeze_pct":97.89,"squeeze_1h_pct":2.11,"ema_sign":1,"ema10_dist_pct":0.3057,"ema10_posture_1h_pct":75.47,"smi_1h":45.1262841606752,"smi_signal_1h":49.54319930492475,"smi_1h_pct":72.56,"smi_bonus_pts":-5,"liquidity_1h":19.59,"volatility_1h_pct":0.44,"volatility_1h_scaled":2.75,"breadth_slow_pct":72.11,"momentum_slow_pct":61.81,"lux_psi_mode_1h":"stateful","completed_1h_bars":449},"hourly":{"sectorDirection1h":{"risingPct":54.55},"riskOn1h":{"riskOnPct":50.0},"overall1h":{"state":"neutral","score":59.85,"components":{"ema10":26.41,"momentum":17.91,"breadth":10.82,"squeeze":0.21,"liquidity":1.14,"volatility":4.86,"riskOn":1.5,"smiBonus":-3.0}},"signals":{"sigOverall1h":{"state":"bull","lastChanged":"2026-05-14T14:17:54Z"}}},"sectorCards":[{"sector":"Communication Services","breadth_pct":67.44,"momentum_pct":49.41,"nh":29,"nl":14,"up":42,"down":43},{"sector":"Consumer Discretionary","breadth_pct":77.27,"momentum_pct":64.41,"nh":68,"nl":20,"up":114,"down":63},{"sector":"Consumer Staples","breadth_pct":63.64,"momentum_pct":39.47,"nh":21,"nl":12,"up":30,"down":46},{"sector":"Energy","breadth_pct":31.82,"momentum_pct":67.06,"nh":14,"nl":30,"up":57,"down":28},{"sector":"Financials","breadth_pct":78.95,"momentum_pct":70.93,"nh":90,"nl":24,"up":222,"down":91},{"sector":"Healthcare","breadth_pct":74.59,"momentum_pct":62.46,"nh":138,"nl":47,"up":223,"down":134},{"sector":"Industrials","breadth_pct":68.0,"momentum_pct":56.89,"nh":68,"nl":32,"up":128,"down":97},{"sector":"Materials","breadth_pct":73.17,"momentum_pct":49.45,"nh":30,"nl":11,"up":45,"down":46},{"sector":"Real Estate","breadth_pct":75.47,"momentum_pct":71.43,"nh":40,"nl":13,"up":60,"down":24},{"sector":"Utilities","breadth_pct":71.43,"momentum_pct":47.62,"nh":15,"nl":6,"up":20,"down":22},{"sector":"tech","breadth_pct":77.78,"momentum_pct":64.77,"nh":105,"nl":30,"up":171,"down":93}],"meta":{"cards_fresh":true,"after_hours":false,"psi_mode_1h":"stateful_lux","fetch_days_1h":40,"completed_1h_bars":449}}