{"sectorCards": [{"sector": "Communication Services", "breadth_pct": 58.82, "momentum_pct": 44.86, "nh": 20, "nl": 14, "up": 48, "down": 59}, {"sector": "Consumer Discretionary", "breadth_pct": 63.77, "momentum_pct": 53.98, "nh": 44, "nl": 25, "up": 95, "down": 81}, {"sector": "Consumer Staples", "breadth_pct": 64.1, "momentum_pct": 50.0, "nh": 25, "nl": 14, "up": 40, "down": 40}, {"sector": "Energy", "breadth_pct": 72.97, "momentum_pct": 65.91, "nh": 27, "nl": 10, "up": 58, "down": 30}, {"sector": "Financials", "breadth_pct": 74.34, "momentum_pct": 64.66, "nh": 84, "nl": 29, "up": 161, "down": 88}, {"sector": "Healthcare", "breadth_pct": 41.1, "momentum_pct": 56.16, "nh": 60, "nl": 86, "up": 187, "down": 146}, {"sector": "Industrials", "breadth_pct": 58.46, "momentum_pct": 47.6, "nh": 38, "nl": 27, "up": 119, "down": 131}, {"sector": "Materials", "breadth_pct": 58.33, "momentum_pct": 63.44, "nh": 14, "nl": 10, "up": 59, "down": 34}, {"sector": "Real Estate", "breadth_pct": 62.5, "momentum_pct": 51.32, "nh": 30, "nl": 18, "up": 39, "down": 37}, {"sector": "Utilities", "breadth_pct": 100.0, "momentum_pct": 40.54, "nh": 7, "nl": 0, "up": 15, "down": 22}, {"sector": "tech", "breadth_pct": 41.89, "momentum_pct": 50.88, "nh": 31, "nl": 43, "up": 145, "down": 140}]}