{"sectorCards": [{"sector": "Communication Services", "breadth_pct": 89.92, "momentum_pct": 78.69, "nh": 107, "nl": 12, "up": 96, "down": 26}, {"sector": "Consumer Discretionary", "breadth_pct": 79.66, "momentum_pct": 72.41, "nh": 188, "nl": 48, "up": 189, "down": 72}, {"sector": "Consumer Staples", "breadth_pct": 80.19, "momentum_pct": 77.27, "nh": 85, "nl": 21, "up": 85, "down": 25}, {"sector": "Energy", "breadth_pct": 22.4, "momentum_pct": 24.14, "nh": 28, "nl": 97, "up": 28, "down": 88}, {"sector": "Financials", "breadth_pct": 90.25, "momentum_pct": 89.39, "nh": 426, "nl": 46, "up": 455, "down": 54}, {"sector": "Healthcare", "breadth_pct": 69.72, "momentum_pct": 62.74, "nh": 327, "nl": 142, "up": 325, "down": 193}, {"sector": "Industrials", "breadth_pct": 62.37, "momentum_pct": 52.42, "nh": 184, "nl": 111, "up": 173, "down": 157}, {"sector": "Materials", "breadth_pct": 78.53, "momentum_pct": 57.41, "nh": 128, "nl": 35, "up": 62, "down": 46}, {"sector": "Real Estate", "breadth_pct": 74.14, "momentum_pct": 83.22, "nh": 86, "nl": 30, "up": 124, "down": 25}, {"sector": "Utilities", "breadth_pct": 32.08, "momentum_pct": 36.51, "nh": 17, "nl": 36, "up": 23, "down": 40}, {"sector": "tech", "breadth_pct": 74.52, "momentum_pct": 66.92, "nh": 310, "nl": 106, "up": 267, "down": 132}]}