{"sectorCards": [{"sector": "Communication Services", "breadth_pct": 43.4, "momentum_pct": 47.06, "nh": 23, "nl": 30, "up": 48, "down": 54}, {"sector": "Consumer Discretionary", "breadth_pct": 60.0, "momentum_pct": 38.07, "nh": 51, "nl": 34, "up": 83, "down": 135}, {"sector": "Consumer Staples", "breadth_pct": 42.0, "momentum_pct": 28.43, "nh": 21, "nl": 29, "up": 29, "down": 73}, {"sector": "Energy", "breadth_pct": 43.48, "momentum_pct": 58.76, "nh": 30, "nl": 39, "up": 57, "down": 40}, {"sector": "Financials", "breadth_pct": 42.68, "momentum_pct": 20.15, "nh": 67, "nl": 90, "up": 81, "down": 321}, {"sector": "Healthcare", "breadth_pct": 65.34, "momentum_pct": 51.45, "nh": 115, "nl": 61, "up": 213, "down": 201}, {"sector": "Industrials", "breadth_pct": 56.52, "momentum_pct": 29.19, "nh": 52, "nl": 40, "up": 94, "down": 228}, {"sector": "Materials", "breadth_pct": 65.91, "momentum_pct": 33.9, "nh": 29, "nl": 15, "up": 40, "down": 78}, {"sector": "Real Estate", "breadth_pct": 70.45, "momentum_pct": 22.52, "nh": 31, "nl": 13, "up": 25, "down": 86}, {"sector": "Utilities", "breadth_pct": 50.0, "momentum_pct": 40.0, "nh": 7, "nl": 7, "up": 12, "down": 18}, {"sector": "tech", "breadth_pct": 71.43, "momentum_pct": 61.04, "nh": 105, "nl": 42, "up": 199, "down": 127}]}