{"sectorCards": [{"sector": "Communication Services", "breadth_pct": 76.0, "momentum_pct": 65.45, "nh": 57, "nl": 18, "up": 72, "down": 38}, {"sector": "Consumer Discretionary", "breadth_pct": 68.9, "momentum_pct": 48.47, "nh": 113, "nl": 51, "up": 111, "down": 118}, {"sector": "Consumer Staples", "breadth_pct": 67.07, "momentum_pct": 50.57, "nh": 55, "nl": 27, "up": 44, "down": 43}, {"sector": "Energy", "breadth_pct": 10.74, "momentum_pct": 15.62, "nh": 16, "nl": 133, "up": 15, "down": 81}, {"sector": "Financials", "breadth_pct": 83.24, "momentum_pct": 72.25, "nh": 288, "nl": 58, "up": 250, "down": 96}, {"sector": "Healthcare", "breadth_pct": 78.07, "momentum_pct": 58.84, "nh": 267, "nl": 75, "up": 223, "down": 156}, {"sector": "Industrials", "breadth_pct": 58.14, "momentum_pct": 34.68, "nh": 125, "nl": 90, "up": 103, "down": 194}, {"sector": "Materials", "breadth_pct": 69.16, "momentum_pct": 44.55, "nh": 74, "nl": 33, "up": 45, "down": 56}, {"sector": "Real Estate", "breadth_pct": 82.09, "momentum_pct": 60.67, "nh": 55, "nl": 12, "up": 54, "down": 35}, {"sector": "Utilities", "breadth_pct": 84.44, "momentum_pct": 57.14, "nh": 38, "nl": 7, "up": 28, "down": 21}, {"sector": "tech", "breadth_pct": 69.53, "momentum_pct": 59.73, "nh": 162, "nl": 71, "up": 178, "down": 120}]}