{"version":"r4h-v7-bodymid-b2-10m-agg","updated_at":"2026-02-05 06:27:05","updated_at_utc":"2026-02-05T13:27:05Z","metrics":{"trend_strength_4h_pct":34.32,"breadth_4h_pct":28.21,"momentum_4h_pct":43.79,"momentum_combo_4h_pct":37.85,"ema_sign_4h":-1,"ema_dist_4h_pct":-0.321,"ema10_posture_4h_pct":32.17,"ema_close_dist_4h_pct":-0.2114,"ema_body_mid_dist_4h_pct":-0.321,"ema_body_top_dist_4h_pct":-0.2114,"ema_wick_reclaimed_4h":false,"ema_reclaim_tol_pct":0.3,"smi_4h":-12.9464,"smi_signal_4h":-1.4102,"smi_4h_pct":43.53,"smi_bonus_pts":-5,"squeeze_psi_4h_pct":51.0,"squeeze_expansion_pct":49.0,"squeeze_pct":51.0,"squeeze_psi_4h":51.0,"squeeze_4h_pct":49.0,"liquidity_4h":44.7,"volatility_4h_pct":0.446,"volatility_4h_scaled":2.79,"sector_dir_4h_pct":9.09,"riskOn_4h_pct":0.0,"psi_window_4h_bars":16,"fetch_days_4h":120},"fourHour":{"sectorDirection4h":{"risingPct":9.09},"riskOn4h":{"riskOnPct":0.0},"overall4h":{"state":"bear","score":34.32,"components":{"ema10":11.26,"momentum":9.46,"breadth":4.23,"squeeze":4.9,"liquidity":2.61,"volatility":4.86,"riskOn":0.0,"smiBonus":-3.0},"lastChanged":"2026-02-05T13:27:05Z"},"signals":{"sigSMI4hBullCross":{"active":false,"reason":"","lastChanged":"2026-02-05T13:27:05Z"},"sigSMI4hBearCross":{"active":false,"reason":"","lastChanged":"2026-02-05T13:27:05Z"}}},"sectorCards":[{"sector":"Communication Services","breadth_pct":43.75,"momentum_pct":43.37,"nh":7,"nl":9,"up":36,"down":47},{"sector":"Consumer Discretionary","breadth_pct":14.81,"momentum_pct":46.3,"nh":4,"nl":23,"up":75,"down":87},{"sector":"Consumer Staples","breadth_pct":50.0,"momentum_pct":46.88,"nh":6,"nl":6,"up":30,"down":34},{"sector":"Energy","breadth_pct":66.67,"momentum_pct":56.41,"nh":4,"nl":2,"up":44,"down":34},{"sector":"Financials","breadth_pct":42.86,"momentum_pct":44.86,"nh":9,"nl":12,"up":96,"down":118},{"sector":"Healthcare","breadth_pct":17.72,"momentum_pct":44.23,"nh":14,"nl":65,"up":157,"down":198},{"sector":"Industrials","breadth_pct":36.84,"momentum_pct":47.66,"nh":14,"nl":24,"up":102,"down":112},{"sector":"Materials","breadth_pct":21.74,"momentum_pct":41.67,"nh":5,"nl":18,"up":30,"down":42},{"sector":"Real Estate","breadth_pct":50.0,"momentum_pct":47.76,"nh":5,"nl":5,"up":32,"down":35},{"sector":"Utilities","breadth_pct":62.5,"momentum_pct":43.75,"nh":5,"nl":3,"up":14,"down":18},{"sector":"tech","breadth_pct":15.0,"momentum_pct":32.41,"nh":6,"nl":34,"up":82,"down":171}],"meta":{"cards_fresh":true,"after_hours":false},"strategy":{"trend4h":{"state":"red","reason":"4H BEAR 34","updatedAt":"2026-02-05T13:27:05Z"}},"engineLights":{"4h":{"state":"bear","score":34.32,"components":{"ema10":11.26,"momentum":9.46,"breadth":4.23,"squeeze":4.9,"liquidity":2.61,"volatility":4.86,"riskOn":0.0,"smiBonus":-3.0},"lastChanged":"2026-02-05T13:27:05Z"}}}