{
  "version": "5m-deltas-r12.8",
  "deltasUpdatedAt": "2026-02-03T16:44:22.573228+00:00",
  "sourceUpdatedAt": "2026-02-03T16:36:38Z",
  "deltas": {
    "sectors": {
      "Information Technology": {
        "netTilt": 0.0
      },
      "Materials": {
        "netTilt": -13.82
      },
      "Health Care": {
        "netTilt": 0.0
      },
      "Communication Services": {
        "netTilt": -36.7
      },
      "Real Estate": {
        "netTilt": -41.34
      },
      "Energy": {
        "netTilt": -28.18
      },
      "Consumer Staples": {
        "netTilt": -10.96
      },
      "Consumer Discretionary": {
        "netTilt": -37.36
      },
      "Financials": {
        "netTilt": -38.12
      },
      "Utilities": {
        "netTilt": -41.49
      },
      "Industrials": {
        "netTilt": -35.25
      },
      "Healthcare": {
        "netTilt": -16.1
      },
      "tech": {
        "netTilt": -37.42
      }
    }
  }
}