{
  "version": "5m-deltas-r12.8",
  "deltasUpdatedAt": "2025-12-05T20:35:55Z",
  "deltas": {
    "sectors": {
      "Information Technology": {
        "netTilt": 0.0
      },
      "Materials": {
        "netTilt": -26.31
      },
      "Health Care": {
        "netTilt": 0.0
      },
      "Communication Services": {
        "netTilt": -8.95
      },
      "Real Estate": {
        "netTilt": -9.15
      },
      "Energy": {
        "netTilt": 0.42
      },
      "Consumer Staples": {
        "netTilt": -4.77
      },
      "Consumer Discretionary": {
        "netTilt": -23.61
      },
      "Financials": {
        "netTilt": -3.73
      },
      "Utilities": {
        "netTilt": 5.75
      },
      "Industrials": {
        "netTilt": -1.19
      },
      "Healthcare": {
        "netTilt": -6.97
      },
      "tech": {
        "netTilt": -10.58
      }
    }
  }
}