{
  "version": "5m-deltas-r12.8",
  "deltasUpdatedAt": "2026-06-04T08:55:53.143403+00:00",
  "sourceUpdatedAt": "2026-06-04T08:52:04Z",
  "deltas": {
    "sectors": {
      "Information Technology": {
        "netTilt": 0.0
      },
      "Materials": {
        "netTilt": -4.77
      },
      "Health Care": {
        "netTilt": 0.0
      },
      "Communication Services": {
        "netTilt": 9.03
      },
      "Real Estate": {
        "netTilt": 0.0
      },
      "Energy": {
        "netTilt": -10.0
      },
      "Consumer Staples": {
        "netTilt": 23.75
      },
      "Consumer Discretionary": {
        "netTilt": -27.98
      },
      "Financials": {
        "netTilt": -10.72
      },
      "Utilities": {
        "netTilt": 4.77
      },
      "Industrials": {
        "netTilt": 9.88
      },
      "Healthcare": {
        "netTilt": 3.97
      },
      "tech": {
        "netTilt": -16.43
      }
    }
  }
}