{
  "version": "5m-deltas-r12.8",
  "deltasUpdatedAt": "2025-12-10T18:19:21.041579+00:00",
  "sourceUpdatedAt": "2025-12-10T18:12:11Z",
  "deltas": {
    "sectors": {
      "Information Technology": {
        "netTilt": 0.0
      },
      "Materials": {
        "netTilt": 25.25
      },
      "Health Care": {
        "netTilt": 0.0
      },
      "Communication Services": {
        "netTilt": 12.23
      },
      "Real Estate": {
        "netTilt": 32.92
      },
      "Energy": {
        "netTilt": 22.78
      },
      "Consumer Staples": {
        "netTilt": 13.23
      },
      "Consumer Discretionary": {
        "netTilt": 17.98
      },
      "Financials": {
        "netTilt": 37.86
      },
      "Utilities": {
        "netTilt": 39.43
      },
      "Industrials": {
        "netTilt": 25.0
      },
      "Healthcare": {
        "netTilt": 19.81
      },
      "tech": {
        "netTilt": 26.22
      }
    }
  }
}