{
  "version": "5m-deltas-r12.8",
  "deltasUpdatedAt": "2025-12-16T22:54:19.414335+00:00",
  "sourceUpdatedAt": "2025-12-16T22:44:59Z",
  "deltas": {
    "sectors": {
      "Information Technology": {
        "netTilt": 0.0
      },
      "Materials": {
        "netTilt": -4.31
      },
      "Health Care": {
        "netTilt": 0.0
      },
      "Communication Services": {
        "netTilt": -8.55
      },
      "Real Estate": {
        "netTilt": -11.94
      },
      "Energy": {
        "netTilt": -19.27
      },
      "Consumer Staples": {
        "netTilt": -15.73
      },
      "Consumer Discretionary": {
        "netTilt": -8.96
      },
      "Financials": {
        "netTilt": -13.49
      },
      "Utilities": {
        "netTilt": -3.17
      },
      "Industrials": {
        "netTilt": -8.84
      },
      "Healthcare": {
        "netTilt": -5.73
      },
      "tech": {
        "netTilt": -4.36
      }
    }
  }
}