{
  "version": "5m-deltas-r12.8",
  "deltasUpdatedAt": "2026-02-24T14:59:21.692031+00:00",
  "sourceUpdatedAt": "2026-02-24T14:56:42Z",
  "deltas": {
    "sectors": {
      "Information Technology": {
        "netTilt": 0.0
      },
      "Materials": {
        "netTilt": 28.09
      },
      "Health Care": {
        "netTilt": 0.0
      },
      "Communication Services": {
        "netTilt": 16.61
      },
      "Real Estate": {
        "netTilt": -6.48
      },
      "Energy": {
        "netTilt": -15.69
      },
      "Consumer Staples": {
        "netTilt": 9.19
      },
      "Consumer Discretionary": {
        "netTilt": 23.99
      },
      "Financials": {
        "netTilt": 24.14
      },
      "Utilities": {
        "netTilt": -16.77
      },
      "Industrials": {
        "netTilt": 23.22
      },
      "Healthcare": {
        "netTilt": 29.06
      },
      "tech": {
        "netTilt": 38.53
      }
    }
  }
}