{
  "version": "5m-deltas-r12.8",
  "deltasUpdatedAt": "2026-03-19T14:14:20.839596+00:00",
  "sourceUpdatedAt": "2026-03-19T14:07:45Z",
  "deltas": {
    "sectors": {
      "Information Technology": {
        "netTilt": 0.0
      },
      "Materials": {
        "netTilt": 24.53
      },
      "Health Care": {
        "netTilt": 0.0
      },
      "Communication Services": {
        "netTilt": 25.87
      },
      "Real Estate": {
        "netTilt": 39.26
      },
      "Energy": {
        "netTilt": 37.14
      },
      "Consumer Staples": {
        "netTilt": 18.1
      },
      "Consumer Discretionary": {
        "netTilt": 33.06
      },
      "Financials": {
        "netTilt": 35.77
      },
      "Utilities": {
        "netTilt": 43.66
      },
      "Industrials": {
        "netTilt": 29.44
      },
      "Healthcare": {
        "netTilt": 10.08
      },
      "tech": {
        "netTilt": 33.82
      }
    }
  }
}