{
  "version": "5m-deltas-r12.8",
  "deltasUpdatedAt": "2026-06-26T15:25:51.334909+00:00",
  "sourceUpdatedAt": "2026-06-26T15:17:33Z",
  "deltas": {
    "sectors": {
      "Information Technology": {
        "netTilt": 0.0
      },
      "Materials": {
        "netTilt": -28.13
      },
      "Health Care": {
        "netTilt": 0.0
      },
      "Communication Services": {
        "netTilt": 18.17
      },
      "Real Estate": {
        "netTilt": 24.35
      },
      "Energy": {
        "netTilt": -20.14
      },
      "Consumer Staples": {
        "netTilt": -3.95
      },
      "Consumer Discretionary": {
        "netTilt": 1.89
      },
      "Financials": {
        "netTilt": 15.73
      },
      "Utilities": {
        "netTilt": 13.52
      },
      "Industrials": {
        "netTilt": -8.42
      },
      "Healthcare": {
        "netTilt": -8.95
      },
      "tech": {
        "netTilt": 8.53
      }
    }
  }
}