{
  "version": "5m-deltas-r12.8",
  "deltasUpdatedAt": "2026-03-06T15:39:21.096772+00:00",
  "sourceUpdatedAt": "2026-03-06T15:29:59Z",
  "deltas": {
    "sectors": {
      "Information Technology": {
        "netTilt": 0.0
      },
      "Materials": {
        "netTilt": 45.28
      },
      "Health Care": {
        "netTilt": 0.0
      },
      "Communication Services": {
        "netTilt": 29.22
      },
      "Real Estate": {
        "netTilt": 11.63
      },
      "Energy": {
        "netTilt": 35.47
      },
      "Consumer Staples": {
        "netTilt": -1.78
      },
      "Consumer Discretionary": {
        "netTilt": 21.77
      },
      "Financials": {
        "netTilt": 23.43
      },
      "Utilities": {
        "netTilt": 15.69
      },
      "Industrials": {
        "netTilt": 35.87
      },
      "Healthcare": {
        "netTilt": 34.72
      },
      "tech": {
        "netTilt": 37.41
      }
    }
  }
}