{
  "version": "5m-deltas-r12.8",
  "deltasUpdatedAt": "2026-05-14T09:25:52.343617+00:00",
  "sourceUpdatedAt": "2026-05-14T09:23:18Z",
  "deltas": {
    "sectors": {
      "Information Technology": {
        "netTilt": 0.0
      },
      "Materials": {
        "netTilt": -0.34
      },
      "Health Care": {
        "netTilt": 0.0
      },
      "Communication Services": {
        "netTilt": -2.27
      },
      "Real Estate": {
        "netTilt": 0.0
      },
      "Energy": {
        "netTilt": 25.0
      },
      "Consumer Staples": {
        "netTilt": -7.73
      },
      "Consumer Discretionary": {
        "netTilt": -10.44
      },
      "Financials": {
        "netTilt": -16.67
      },
      "Utilities": {
        "netTilt": -12.5
      },
      "Industrials": {
        "netTilt": -33.23
      },
      "Healthcare": {
        "netTilt": -20.1
      },
      "tech": {
        "netTilt": -20.19
      }
    }
  }
}