{
  "version": "5m-deltas-r12.8",
  "deltasUpdatedAt": "2026-04-14T09:55:52.236643+00:00",
  "sourceUpdatedAt": "2026-04-14T09:51:57Z",
  "deltas": {
    "sectors": {
      "Information Technology": {
        "netTilt": 0.0
      },
      "Materials": {
        "netTilt": -11.33
      },
      "Health Care": {
        "netTilt": 0.0
      },
      "Communication Services": {
        "netTilt": -18.48
      },
      "Real Estate": {
        "netTilt": 4.16
      },
      "Energy": {
        "netTilt": -16.52
      },
      "Consumer Staples": {
        "netTilt": -13.34
      },
      "Consumer Discretionary": {
        "netTilt": -11.3
      },
      "Financials": {
        "netTilt": -28.59
      },
      "Utilities": {
        "netTilt": -20.84
      },
      "Industrials": {
        "netTilt": 4.47
      },
      "Healthcare": {
        "netTilt": -0.84
      },
      "tech": {
        "netTilt": -11.19
      }
    }
  }
}