{
  "version": "5m-deltas-r12.8",
  "deltasUpdatedAt": "2026-04-10T20:05:51.864187+00:00",
  "sourceUpdatedAt": "2026-04-10T19:56:45Z",
  "deltas": {
    "sectors": {
      "Information Technology": {
        "netTilt": 0.0
      },
      "Materials": {
        "netTilt": -18.49
      },
      "Health Care": {
        "netTilt": 0.0
      },
      "Communication Services": {
        "netTilt": -6.24
      },
      "Real Estate": {
        "netTilt": -2.73
      },
      "Energy": {
        "netTilt": -8.97
      },
      "Consumer Staples": {
        "netTilt": -7.6
      },
      "Consumer Discretionary": {
        "netTilt": -10.69
      },
      "Financials": {
        "netTilt": -25.75
      },
      "Utilities": {
        "netTilt": -27.49
      },
      "Industrials": {
        "netTilt": -14.58
      },
      "Healthcare": {
        "netTilt": -6.76
      },
      "tech": {
        "netTilt": -20.04
      }
    }
  }
}