{
  "version": "5m-deltas-r12.8",
  "deltasUpdatedAt": "2026-02-25T14:19:21.866678+00:00",
  "sourceUpdatedAt": "2026-02-25T14:12:02Z",
  "deltas": {
    "sectors": {
      "Information Technology": {
        "netTilt": 0.0
      },
      "Materials": {
        "netTilt": 8.52
      },
      "Health Care": {
        "netTilt": 0.0
      },
      "Communication Services": {
        "netTilt": 5.12
      },
      "Real Estate": {
        "netTilt": -28.19
      },
      "Energy": {
        "netTilt": -0.59
      },
      "Consumer Staples": {
        "netTilt": -16.67
      },
      "Consumer Discretionary": {
        "netTilt": 5.78
      },
      "Financials": {
        "netTilt": 14.91
      },
      "Utilities": {
        "netTilt": -8.34
      },
      "Industrials": {
        "netTilt": 11.25
      },
      "Healthcare": {
        "netTilt": 5.87
      },
      "tech": {
        "netTilt": 8.19
      }
    }
  }
}