{
  "version": "5m-deltas-r12.8",
  "deltasUpdatedAt": "2026-02-10T17:14:21.975426+00:00",
  "sourceUpdatedAt": "2026-02-10T17:09:25Z",
  "deltas": {
    "sectors": {
      "Information Technology": {
        "netTilt": 0.0
      },
      "Materials": {
        "netTilt": 14.81
      },
      "Health Care": {
        "netTilt": 0.0
      },
      "Communication Services": {
        "netTilt": -4.48
      },
      "Real Estate": {
        "netTilt": 6.28
      },
      "Energy": {
        "netTilt": -13.12
      },
      "Consumer Staples": {
        "netTilt": -20.03
      },
      "Consumer Discretionary": {
        "netTilt": -10.63
      },
      "Financials": {
        "netTilt": 13.06
      },
      "Utilities": {
        "netTilt": 19.97
      },
      "Industrials": {
        "netTilt": 2.7
      },
      "Healthcare": {
        "netTilt": 6.03
      },
      "tech": {
        "netTilt": -18.56
      }
    }
  }
}