{
  "version": "5m-deltas-r12.8",
  "deltasUpdatedAt": "2025-12-15T17:04:19.203095+00:00",
  "sourceUpdatedAt": "2025-12-15T16:53:36Z",
  "deltas": {
    "sectors": {
      "Information Technology": {
        "netTilt": 0.0
      },
      "Materials": {
        "netTilt": -35.35
      },
      "Health Care": {
        "netTilt": 0.0
      },
      "Communication Services": {
        "netTilt": -32.47
      },
      "Real Estate": {
        "netTilt": -17.78
      },
      "Energy": {
        "netTilt": -41.19
      },
      "Consumer Staples": {
        "netTilt": -18.38
      },
      "Consumer Discretionary": {
        "netTilt": -25.9
      },
      "Financials": {
        "netTilt": -21.21
      },
      "Utilities": {
        "netTilt": -14.1
      },
      "Industrials": {
        "netTilt": -34.48
      },
      "Healthcare": {
        "netTilt": -28.16
      },
      "tech": {
        "netTilt": -38.84
      }
    }
  }
}