{
  "version": "5m-deltas-r12.8",
  "deltasUpdatedAt": "2026-01-02T18:09:18.442755+00:00",
  "sourceUpdatedAt": "2026-01-02T18:04:21Z",
  "deltas": {
    "sectors": {
      "Information Technology": {
        "netTilt": 0.0
      },
      "Materials": {
        "netTilt": -25.32
      },
      "Health Care": {
        "netTilt": 0.0
      },
      "Communication Services": {
        "netTilt": -7.23
      },
      "Real Estate": {
        "netTilt": 0.0
      },
      "Energy": {
        "netTilt": 10.7
      },
      "Consumer Staples": {
        "netTilt": -6.57
      },
      "Consumer Discretionary": {
        "netTilt": -22.04
      },
      "Financials": {
        "netTilt": -23.88
      },
      "Utilities": {
        "netTilt": -2.42
      },
      "Industrials": {
        "netTilt": -22.66
      },
      "Healthcare": {
        "netTilt": -4.03
      },
      "tech": {
        "netTilt": -22.48
      }
    }
  }
}