{
  "version": "5m-deltas-r12.8",
  "deltasUpdatedAt": "2026-07-20T17:10:54.248627+00:00",
  "sourceUpdatedAt": "2026-07-20T17:02:25Z",
  "deltas": {
    "sectors": {
      "Information Technology": {
        "netTilt": 0.0
      },
      "Materials": {
        "netTilt": -27.91
      },
      "Health Care": {
        "netTilt": 0.0
      },
      "Communication Services": {
        "netTilt": -28.52
      },
      "Real Estate": {
        "netTilt": 7.72
      },
      "Energy": {
        "netTilt": 3.23
      },
      "Consumer Staples": {
        "netTilt": -12.49
      },
      "Consumer Discretionary": {
        "netTilt": -30.61
      },
      "Financials": {
        "netTilt": -34.04
      },
      "Utilities": {
        "netTilt": 1.47
      },
      "Industrials": {
        "netTilt": -29.2
      },
      "Healthcare": {
        "netTilt": 5.97
      },
      "tech": {
        "netTilt": -33.43
      }
    }
  }
}